__init__.py
context_timing/__init__.py
context_timing/context_timing.py
context_timing-0.0.2.dist-info/LICENSE
context_timing-0.0.2.dist-info/METADATA
context_timing-0.0.2.dist-info/WHEEL
context_timing-0.0.2.dist-info/top_level.txt
context_timing-0.0.2.dist-info/RECORD
