Metadata-Version: 2.1
Name: context-timing
Version: 0.0.2
Summary: Yet another way to measure code execution duration using a context
License: MIT License
Project-URL: Homepage, https://github.com/patou01/context-timing
Project-URL: Issues, https://github.com/patou01/context-timing/issues
Classifier: Programming Language :: Python :: 3
Classifier: License :: OSI Approved :: MIT License
Classifier: Operating System :: OS Independent
Classifier: Development Status :: 4 - Beta
Requires-Python: >=3
License-File: LICENSE
